README.rst
setup.cfg
setup.py
vaud/__init__.py
vaud/al_audio.py
vaud/decoder.py
vaud.egg-info/PKG-INFO
vaud.egg-info/SOURCES.txt
vaud.egg-info/dependency_links.txt
vaud.egg-info/not-zip-safe
vaud.egg-info/top_level.txt