Metadata-Version: 1.1
Name: vaud
Version: 0.3.4
Summary: Simple vk.com audio address decoder
Home-page: https://github.com/yuru-yuri/vk-audio-url-decoder/
Author: Zharkov Sergey
Author-email: sttvpc@gmail.com
License: MIT
Download-URL: https://github.com/yuru-yuri/vk-audio-url-decoder/archive/0.3.4.tar.gz
Keywords: vk.com audio address decoder,vk music
Platform: UNKNOWN
Classifier: Intended Audience :: Developers
Classifier: Programming Language :: Python
Classifier: Programming Language :: Python :: 2
Classifier: Programming Language :: Python :: 2.7
Classifier: Programming Language :: Python :: 3
Classifier: Programming Language :: Python :: 3.4
Classifier: Programming Language :: Python :: 3.5
Classifier: Programming Language :: Python :: 3.6
Classifier: Programming Language :: Python :: Implementation :: PyPy
Classifier: Topic :: Internet :: WWW/HTTP :: Dynamic Content
Classifier: License :: OSI Approved :: MIT License
